trelliolibs
