Metadata-Version: 1.0
Name: trelliolibs
Version: 0.37.3
Summary: Utilities for trellio framework
Home-page: https://github.com/zoniclabs/trelliolibs
Author: Abhishek Verma, Nirmal Singh
Author-email: ashuverma1989@gmail.com, nirmal.singh.cer08@itbhu.ac.in
License: UNKNOWN
Platform: UNKNOWN
